weaverbird/__init__.py
weaverbird/exceptions.py
weaverbird/backends/__init__.py
weaverbird/backends/mongo_translator/__init__.py
weaverbird/backends/mongo_translator/date_extractors.py
weaverbird/backends/mongo_translator/mongo_pipeline_translator.py
weaverbird/backends/mongo_translator/utils.py
weaverbird/backends/mongo_translator/steps/__init__.py
weaverbird/backends/mongo_translator/steps/absolutevalue.py
weaverbird/backends/mongo_translator/steps/addmissingdates.py
weaverbird/backends/mongo_translator/steps/aggregate.py
weaverbird/backends/mongo_translator/steps/append.py
weaverbird/backends/mongo_translator/steps/argmax.py
weaverbird/backends/mongo_translator/steps/argmin.py
weaverbird/backends/mongo_translator/steps/comparetext.py
weaverbird/backends/mongo_translator/steps/concatenate.py
weaverbird/backends/mongo_translator/steps/convert.py
weaverbird/backends/mongo_translator/steps/cumsum.py
weaverbird/backends/mongo_translator/steps/custom.py
weaverbird/backends/mongo_translator/steps/date_extract.py
weaverbird/backends/mongo_translator/steps/date_granularity.py
weaverbird/backends/mongo_translator/steps/delete.py
weaverbird/backends/mongo_translator/steps/domain.py
weaverbird/backends/mongo_translator/steps/duplicate.py
weaverbird/backends/mongo_translator/steps/duration.py
weaverbird/backends/mongo_translator/steps/evolution.py
weaverbird/backends/mongo_translator/steps/fillna.py
weaverbird/backends/mongo_translator/steps/filter.py
weaverbird/backends/mongo_translator/steps/formula.py
weaverbird/backends/mongo_translator/steps/fromdate.py
weaverbird/backends/mongo_translator/steps/ifthenelse.py
weaverbird/backends/mongo_translator/steps/join.py
weaverbird/backends/mongo_translator/steps/lowercase.py
weaverbird/backends/mongo_translator/steps/moving_average.py
weaverbird/backends/mongo_translator/steps/percentage.py
weaverbird/backends/mongo_translator/steps/pivot.py
weaverbird/backends/mongo_translator/steps/rank.py
weaverbird-0.62.0.dist-info/METADATA
weaverbird-0.62.0.dist-info/WHEEL
weaverbird-0.62.0.dist-info/top_level.txt
weaverbird-0.62.0.dist-info/RECORD
