Metadata-Version: 2.4
Name: weaverbird
Version: 0.62.0
Summary: A visual data pipeline builder with various backends
Author-email: Toucan Toco <dev@toucantoco.com>
License-Expression: BSD-3-Clause
Keywords: builder,data,dataviz,mongodb,pandas,pipeline,query,sql
Requires-Python: <3.14,>=3.13
Requires-Dist: pydantic<3.0.0,>=2.4.2
Requires-Dist: python-dateutil<3.0.0,>=2.8.2
Provides-Extra: pandas
Requires-Dist: pandas<3,>=2; extra == "pandas"
Requires-Dist: geopandas<2; extra == "pandas"
Provides-Extra: pypika
Requires-Dist: pypika>=0.48.9; extra == "pypika"
Provides-Extra: all
Requires-Dist: pandas<3,>=2; extra == "all"
Requires-Dist: geopandas<2; extra == "all"
Requires-Dist: pypika>=0.48.9; extra == "all"
